autilities/__devel__.py
autilities/__init__.py
autilities/kubernetes/__init__.py
autilities/kubernetes/__sane__.py
autilities/kubernetes/kubectl.py
autilities/pythonic/__init__.py
autilities/pythonic/modules.py
autilities/pythonic/packaging.py
autilities/pythonic/stack.py
autilities/shell.py
autilities/subnet/__init__.py
autilities/subnet/get_host.py
autilities/subnet/get_local_ip.py
autilities/testing/__init__.py
autilities/testing/tracing.py
autilities/testing/watch.py
autilities/uv/__init__.py
autilities-0.2.0.dist-info/WHEEL
autilities-0.2.0.dist-info/WHEEL.json
autilities-0.2.0.dist-info/entry_points.txt
autilities-0.2.0.dist-info/METADATA
autilities-0.2.0.dist-info/METADATA.json
autilities-0.2.0.dist-info/RECORD
