Metadata-Version: 2.3
Name: autilities
Version: 0.2.0
Summary: utility functions
Requires-Dist: parlancy
Requires-Dist: twine>=6.2.0
Requires-Dist: watchdog>=6.0.0
Requires-Python: >=3.12
